{
  "users": [
    {
      "id": "1",
      "name": "hesam mahmoodi",
      "email": "hesam@gmail.com",
      "password": "123456",
      "token": "1234567890"
    },
    {
      "name": "yas",
      "email": "y.janfeshani@gmail.com",
      "password": "12345",
      "token": "1234567890",
      "id": "_h_pt9h"
    },
    {
      "name": "yasi",
      "email": "yasi@gmail.com",
      "password": "123456",
      "token": "1234567890",
      "id": "s0jCtGu"
    }
  ],
  "tasks": [
    {
      "id": 1
    },
    {
      "id": 2,
      "title": "123",
      "description": "1234",
      "priority": "medium",
      "stage": "done",
      "assign_to": "",
      "date": 1707833165174,
      "user": "hesam mahmoodi"
    }
  ]
}